mhlog/__init__.py
mhlog/logger.py
mhlog-0.1.6.dist-info/LICENSE
mhlog-0.1.6.dist-info/METADATA
mhlog-0.1.6.dist-info/WHEEL
mhlog-0.1.6.dist-info/top_level.txt
mhlog-0.1.6.dist-info/RECORD
