Metadata-Version: 2.1
Name: mhlog
Version: 0.1.6
Summary: Simple logging library.
Home-page: UNKNOWN
Author: Magnus Hirth
Author-email: mhmorgan42@gmail.com
License: UNKNOWN
Platform: UNKNOWN
Classifier: Programming Language :: Python :: 3
